ghpusher/__init__.py
ghpusher/gh_pusher.py
ghpusher-0.2.2.dist-info/entry_points.txt
ghpusher-0.2.2.dist-info/LICENSE
ghpusher-0.2.2.dist-info/WHEEL
ghpusher-0.2.2.dist-info/METADATA
ghpusher-0.2.2.dist-info/RECORD
