Metadata-Version: 2.1
Name: ghpusher
Version: 0.2.2
Summary: Push HTML to a github pages branch
Home-page: https://github.com/dbradf/gh-pusher
License: Apache-2.0
Author: David Bradford
Author-email: david.bradford@mongodb.com
Requires-Python: >=3.6,<4.0
Classifier: License :: OSI Approved :: Apache Software License
Classifier: Programming Language :: Python :: 3
Classifier: Programming Language :: Python :: 3.6
Classifier: Programming Language :: Python :: 3.7
Classifier: Programming Language :: Python :: 3.8
Requires-Dist: Click (>=7.0,<8.0)
Requires-Dist: plumbum (>=1.6.9,<2.0.0)
Project-URL: Repository, https://github.com/dbradf/gh-pusher
